{
  "pie_plus": [
    {
      "md5": "4b1b1f2f679fe110897802f62d3da83a",
      "file_size": 907981632,
      "file_name": "PixelExperience_Plus_hero2lte-9.0-20190822-2228-OFFICIAL.zip"
    },
    {
      "md5": "8184ce2347787cc6f36ac7bcf0ebd4cb",
      "file_size": 909960429,
      "file_name": "PixelExperience_Plus_hero2lte-9.0-20190919-1950-OFFICIAL.zip"
    }
  ],
  "pie": [
    {
      "md5": "8544b9ba0226c3caed4d1201a709104e",
      "file_size": 880693787,
      "file_name": "PixelExperience_hero2lte-9.0-20190317-0015-OFFICIAL.zip"
    },
    {
      "md5": "6639478120c60c880578448ca524751a",
      "file_size": 881508176,
      "file_name": "PixelExperience_hero2lte-9.0-20190317-2245-OFFICIAL.zip"
    },
    {
      "md5": "a251bdfec259e60949c2b4ad25641d53",
      "file_size": 881514617,
      "file_name": "PixelExperience_hero2lte-9.0-20190323-2327-OFFICIAL.zip"
    },
    {
      "md5": "5353dd1c64ca74699c9e5390c9959c08",
      "file_size": 881018416,
      "file_name": "PixelExperience_hero2lte-9.0-20190404-0104-OFFICIAL.zip"
    },
    {
      "md5": "2251f9b3c5c392039c6da07b533a1c5e",
      "file_size": 881209623,
      "file_name": "PixelExperience_hero2lte-9.0-20190418-0129-OFFICIAL.zip"
    },
    {
      "md5": "3b52046c3863745b648867b34a5373ee",
      "file_size": 881171861,
      "file_name": "PixelExperience_hero2lte-9.0-20190424-2200-OFFICIAL.zip"
    },
    {
      "md5": "17df0d864515874f92615e0eb9c9704e",
      "file_size": 893155886,
      "file_name": "PixelExperience_hero2lte-9.0-20190507-1044-OFFICIAL.zip"
    },
    {
      "md5": "04e14c6fdbecee18b52965e611f36d08",
      "file_size": 892866921,
      "file_name": "PixelExperience_hero2lte-9.0-20190515-1323-OFFICIAL.zip"
    },
    {
      "md5": "9d36a65e8eb99404d107ae3ffd62738f",
      "file_size": 898978651,
      "file_name": "PixelExperience_hero2lte-9.0-20190604-0908-OFFICIAL.zip"
    },
    {
      "md5": "59b936383b52e2edf672373cbe5ba90e",
      "file_size": 906429732,
      "file_name": "PixelExperience_hero2lte-9.0-20190823-0257-OFFICIAL.zip"
    },
    {
      "md5": "789acb8f59cf07684e103e865eb2e758",
      "file_size": 906893974,
      "file_name": "PixelExperience_hero2lte-9.0-20190919-1404-OFFICIAL.zip"
    }
  ]
}